Workbook

Sheet Synthèse
A1: Ads diffusées & CTR — septembre 2026
A2: Annonces directes Lemrock Media Network, 1–30 septembre 2026 (UTC). CTR = clics / impressions.
A4: Client | B4: Statut | C4: Nb ads diffusées | D4: Impressions | E4: Clics | F4: CTR | G4: Remarque
A5: Clients Live
A6: Boulanger | B6: Live | C6: =COUNTIFS('Détail par ad'!$A$2:$A$2174,A6) | D6: =SUMIFS('Détail par ad'!$H$2:$H$2174,'Détail par ad'!$A$2:$A$2174,A6) | E6: =SUMIFS('Détail par ad'!$I$2:$I$2174,'Détail par ad'!$A$2:$A$2174,A6) | F6: =IF(D6=0,"—",E6/D6)
A7: Cdiscount Voyages | B7: Live | C7: =COUNTIFS('Détail par ad'!$A$2:$A$2174,A7) | D7: =SUMIFS('Détail par ad'!$H$2:$H$2174,'Détail par ad'!$A$2:$A$2174,A7) | E7: =SUMIFS('Détail par ad'!$I$2:$I$2174,'Détail par ad'!$A$2:$A$2174,A7) | F7: =IF(D7=0,"—",E7/D7)
A8: Monoprix | B8: Live | C8: =COUNTIFS('Détail par ad'!$A$2:$A$2174,A8) | D8: =SUMIFS('Détail par ad'!$H$2:$H$2174,'Détail par ad'!$A$2:$A$2174,A8) | E8: =SUMIFS('Détail par ad'!$I$2:$I$2174,'Détail par ad'!$A$2:$A$2174,A8) | F8: =IF(D8=0,"—",E8/D8)
A9: Cdiscount Mobile | B9: Live | C9: =COUNTIFS('Détail par ad'!$A$2:$A$2174,A9) | D9: =SUMIFS('Détail par ad'!$H$2:$H$2174,'Détail par ad'!$A$2:$A$2174,A9) | E9: =SUMIFS('Détail par ad'!$I$2:$I$2174,'Détail par ad'!$A$2:$A$2174,A9) | F9: =IF(D9=0,"—",E9/D9)
A10: Qonto | B10: Live | C10: =COUNTIFS('Détail par ad'!$A$2:$A$2174,A10) | D10: =SUMIFS('Détail par ad'!$H$2:$H$2174,'Détail par ad'!$A$2:$A$2174,A10) | E10: =SUMIFS('Détail par ad'!$I$2:$I$2174,'Détail par ad'!$A$2:$A$2174,A10) | F10: =IF(D10=0,"—",E10/D10)
A11: Basket4ballers | B11: Live | C11: =COUNTIFS('Détail par ad'!$A$2:$A$2174,A11) | D11: =SUMIFS('Détail par ad'!$H$2:$H$2174,'Détail par ad'!$A$2:$A$2174,A11) | E11: =SUMIFS('Détail par ad'!$I$2:$I$2174,'Détail par ad'!$A$2:$A$2174,A11) | F11: =IF(D11=0,"—",E11/D11)
A12: FidMe | B12: Live | C12: =COUNTIFS('Détail par ad'!$A$2:$A$2174,A12) | D12: =SUMIFS('Détail par ad'!$H$2:$H$2174,'Détail par ad'!$A$2:$A$2174,A12) | E12: =SUMIFS('Détail par ad'!$I$2:$I$2174,'Détail par ad'!$A$2:$A$2174,A12) | F12: =IF(D12=0,"—",E12/D12)
A13: Pour de Bon | B13: Live | C13: =COUNTIFS('Détail par ad'!$A$2:$A$2174,A13) | D13: =SUMIFS('Détail par ad'!$H$2:$H$2174,'Détail par ad'!$A$2:$A$2174,A13) | E13: =SUMIFS('Détail par ad'!$I$2:$I$2174,'Détail par ad'!$A$2:$A$2174,A13) | F13: =IF(D13=0,"—",E13/D13)
A14: PV | B14: Live | C14: =COUNTIFS('Détail par ad'!$A$2:$A$2174,A14) | D14: =SUMIFS('Détail par ad'!$H$2:$H$2174,'Détail par ad'!$A$2:$A$2174,A14) | E14: =SUMIFS('Détail par ad'!$I$2:$I$2174,'Détail par ad'!$A$2:$A$2174,A14) | F14: =IF(D14=0,"—",E14/D14)
A15: Allo Pneus | B15: Live | C15: =COUNTIFS('Détail par ad'!$A$2:$A$2174,A15) | D15: =SUMIFS('Détail par ad'!$H$2:$H$2174,'Détail par ad'!$A$2:$A$2174,A15) | E15: =SUMIFS('Détail par ad'!$I$2:$I$2174,'Détail par ad'!$A$2:$A$2174,A15) | F15: =IF(D15=0,"—",E15/D15)
A16: Marshall | B16: Live | C16: =COUNTIFS('Détail par ad'!$A$2:$A$2174,A16) | D16: =SUMIFS('Détail par ad'!$H$2:$H$2174,'Détail par ad'!$A$2:$A$2174,A16) | E16: =SUMIFS('Détail par ad'!$I$2:$I$2174,'Détail par ad'!$A$2:$A$2174,A16) | F16: =IF(D16=0,"—",E16/D16)
A17: Dorel | B17: Live | C17: =COUNTIFS('Détail par ad'!$A$2:$A$2174,A17) | D17: =SUMIFS('Détail par ad'!$H$2:$H$2174,'Détail par ad'!$A$2:$A$2174,A17) | E17: =SUMIFS('Détail par ad'!$I$2:$I$2174,'Détail par ad'!$A$2:$A$2174,A17) | F17: =IF(D17=0,"—",E17/D17)
... A22: Archipel Kombucha | B22: Live | C22: =COUNTIFS('Détail par ad'!$A$2:$A$2174,A22) | D22: =SUMIFS('Détail par ad'!$H$2:$H$2174,'Détail par ad'!$A$2:$A$2174,A22) | E22: =SUMIFS('Détail par ad'!$I$2:$I$2174,'Détail par ad'!$A$2:$A$2174,A22) | F22: =IF(D22=0,"—",E22/D22)
A23: SNCF | B23: Live | C23: =COUNTIFS('Détail par ad'!$A$2:$A$2174,A23) | D23: =SUMIFS('Détail par ad'!$H$2:$H$2174,'Détail par ad'!$A$2:$A$2174,A23) | E23: =SUMIFS('Détail par ad'!$I$2:$I$2174,'Détail par ad'!$A$2:$A$2174,A23) | F23: =IF(D23=0,"—",E23/D23) | G23: Lancé le 30/09 : 1 seul jour de diffusion en septembre
A24: Elhée | B24: Live | C24: =COUNTIFS('Détail par ad'!$A$2:$A$2174,A24) | D24: =SUMIFS('Détail par ad'!$H$2:$H$2174,'Détail par ad'!$A$2:$A$2174,A24) | E24: =SUMIFS('Détail par ad'!$I$2:$I$2174,'Détail par ad'!$A$2:$A$2174,A24) | F24: =IF(D24=0,"—",E24/D24) | G24: Lancé le 07/10 : aucune diffusion en septembre
A25: Mabex | B25: Live | C25: =COUNTIFS('Détail par ad'!$A$2:$A$2174,A25) | D25: =SUMIFS('Détail par ad'!$H$2:$H$2174,'Détail par ad'!$A$2:$A$2174,A25) | E25: =SUMIFS('Détail par ad'!$I$2:$I$2174,'Détail par ad'!$A$2:$A$2174,A25) | F25: =IF(D25=0,"—",E25/D25) | G25: Aucune diffusion trouvée en septembre
A26: Sous-total | C26: =SUM(C6:C25) | D26: =SUM(D6:D25) | E26: =SUM(E6:E25) | F26: =IF(D26=0,"—",E26/D26)
A28: Clients en fin de campagne (diffusés en septembre)
A29: Ryobi | B29: Terminé | C29: =COUNTIFS('Détail par ad'!$A$2:$A$2174,A29) | D29: =SUMIFS('Détail par ad'!$H$2:$H$2174,'Détail par ad'!$A$2:$A$2174,A29) | E29: =SUMIFS('Détail par ad'!$I$2:$I$2174,'Détail par ad'!$A$2:$A$2174,A29) | F29: =IF(D29=0,"—",E29/D29)
A30: Iopole | B30: Terminé | C30: =COUNTIFS('Détail par ad'!$A$2:$A$2174,A30) | D30: =SUMIFS('Détail par ad'!$H$2:$H$2174,'Détail par ad'!$A$2:$A$2174,A30) | E30: =SUMIFS('Détail par ad'!$I$2:$I$2174,'Détail par ad'!$A$2:$A$2174,A30) | F30: =IF(D30=0,"—",E30/D30)
A31: La redoute | B31: Terminé | C31: =COUNTIFS('Détail par ad'!$A$2:$A$2174,A31) | D31: =SUMIFS('Détail par ad'!$H$2:$H$2174,'Détail par ad'!$A$2:$A$2174,A31) | E31: =SUMIFS('Détail par ad'!$I$2:$I$2174,'Détail par ad'!$A$2:$A$2174,A31) | F31: =IF(D31=0,"—",E31/D31)
A32: Bayard Jeunesse | B32: Terminé | C32: =COUNTIFS('Détail par ad'!$A$2:$A$2174,A32) | D32: =SUMIFS('Détail par ad'!$H$2:$H$2174,'Détail par ad'!$A$2:$A$2174,A32) | E32: =SUMIFS('Détail par ad'!$I$2:$I$2174,'Détail par ad'!$A$2:$A$2174,A32) | F32: =IF(D32=0,"—",E32/D32)
A33: Franklin Pet Food | B33: Terminé | C33: =COUNTIFS('Détail par ad'!$A$2:$A$2174,A33) | D33: =SUMIFS('Détail par ad'!$H$2:$H$2174,'Détail par ad'!$A$2:$A$2174,A33) | E33: =SUMIFS('Détail par ad'!$I$2:$I$2174,'Détail par ad'!$A$2:$A$2174,A33) | F33: =IF(D33=0,"—",E33/D33)
A34: 1001 Pneus | B34: Terminé | C34: =COUNTIFS('Détail par ad'!$A$2:$A$2174,A34) | D34: =SUMIFS('Détail par ad'!$H$2:$H$2174,'Détail par ad'!$A$2:$A$2174,A34) | E34: =SUMIFS('Détail par ad'!$I$2:$I$2174,'Détail par ad'!$A$2:$A$2174,A34) | F34: =IF(D34=0,"—",E34/D34)
A35: La marque en moins | B35: Terminé | C35: =COUNTIFS('Détail par ad'!$A$2:$A$2174,A35) | D35: =SUMIFS('Détail par ad'!$H$2:$H$2174,'Détail par ad'!$A$2:$A$2174,A35) | E35: =SUMIFS('Détail par ad'!$I$2:$I$2174,'Détail par ad'!$A$2:$A$2174,A35) | F35: =IF(D35=0,"—",E35/D35)
A36: Ultra Premium Direct | B36: Terminé | C36: =COUNTIFS('Détail par ad'!$A$2:$A$2174,A36) | D36: =SUMIFS('Détail par ad'!$H$2:$H$2174,'Détail par ad'!$A$2:$A$2174,A36) | E36: =SUMIFS('Détail par ad'!$I$2:$I$2174,'Détail par ad'!$A$2:$A$2174,A36) | F36: =IF(D36=0,"—",E36/D36)
A37: Sous-total | C37: =SUM(C29:C36) | D37: =SUM(D29:D36) | E37: =SUM(E29:E36) | F37: =IF(D37=0,"—",E37/D37)
A39: Hors fichier de suivi
A40: MINI | B40: Hors fichier de suivi | C40: =COUNTIFS('Détail par ad'!$A$2:$A$2174,A40) | D40: =SUMIFS('Détail par ad'!$H$2:$H$2174,'Détail par ad'!$A$2:$A$2174,A40) | E40: =SUMIFS('Détail par ad'!$I$2:$I$2174,'Détail par ad'!$A$2:$A$2174,A40) | F40: =IF(D40=0,"—",E40/D40) | G40: Annonceur absent du fichier de suivi
A41: Comptoir des Pros | B41: Hors fichier de suivi | C41: =COUNTIFS('Détail par ad'!$A$2:$A$2174,A41) | D41: =SUMIFS('Détail par ad'!$H$2:$H$2174,'Détail par ad'!$A$2:$A$2174,A41) | E41: =SUMIFS('Détail par ad'!$I$2:$I$2174,'Détail par ad'!$A$2:$A$2174,A41) | F41: =IF(D41=0,"—",E41/D41) | G41: Annonceur absent du fichier de suivi
A42: Sous-total | C42: =SUM(C40:C41) | D42: =SUM(D40:D41) | E42: =SUM(E40:E41) | F42: =IF(D42=0,"—",E42/D42)
A44: TOTAL | C44: =C26+C37+C42 | D44: =D26+D37+D42 | E44: =E26+E37+E42 | F44: =IF(D44=0,"—",E44/D44)

Sheet Détail par ad
A1: Client | B1: Statut | C1: Campagne | D1: Groupe d'annonces | E1: Titre de l'ad | F1: Description | G1: URL de destination | H1: Impressions | I1: Clics | J1: CTR
A2: Boulanger | B2: Live | C2: Boulanger | D2: Enceintes et barres de son | E2: Barre de son BOSE TV Speaker | F2: Une barre compacte qui rend les dialogues de vos films plus clairs, branchée d’un seul câble sous la télé. Livraison offerte et garantie 2 ans chez Boulanger. | G2: https://www.boulanger.com/ref/1145344?at_medium=gea&at_campaign=lemrock | H2: 52227 | I2: 147 | J2: =IF(H2=0,0,I2/H2)
A3: Boulanger | B3: Live | C3: Boulanger | D3: Smartphones et accessoires | E3: Smartphone SAMSUNG Galaxy S24 Ultra Gris | F3: Bienvenue dans la nouvelle ère de l'Intelligence Artificielle mobile. Entre vos mains, le Galaxy S24 Ultra vous ouvre de nouveaux horizons. Productifs d'abord, avec des | G3: https://www.boulanger.com/ref/1200027?at_medium=gea&at_campaign=lemrock | H3: 42500 | I3: 217 | J3: =IF(H3=0,0,I3/H3)
A4: Boulanger | B4: Live | C4: Boulanger | D4: Consoles de jeux | E4: Console Portable ASUS Rog Xbox Ally | F4: Console portable Asus qui fait tourner vos jeux Xbox et PC partout, sans télé ; reprise de votre ancienne console et retrait en une heure en magasin Boulanger. | G4: https://www.boulanger.com/ref/1224182?at_medium=gea&at_campaign=lemrock | H4: 40605 | I4: 1390 | J4: =IF(H4=0,0,I4/H4)
A5: Boulanger | B5: Live | C5: Boulanger | D5: Consoles de jeux | E5: Console NINTENDO Switch 2 | F5: La nouvelle console Nintendo, jouable sur la TV ou en déplacement, pour toute la famille ; retirez la Switch 2 en une heure dans votre magasin Boulanger, garantie 2 ans. | G5: https://www.boulanger.com/ref/1220464?at_medium=gea&at_campaign=lemrock | H5: 39174 | I5: 346 | J5: =IF(H5=0,0,I5/H5)
A6: Boulanger | B6: Live | C6: Boulanger | D6: Consumer Electronics | E6: Informatique, son et téléphonie prix bas | Boulanger | F6: Chargeur secteur Watt and Co Uni. 3000 mAh : une solution de charge universelle, compatible avec la plupart de vos appareils, à retrouver chez Boulanger. | G6: https://www.boulanger.com/ref/151244?at_medium=gea&at_campaign=lemrock | H6: 38962 | I6: 373 | J6: =IF(H6=0,0,I6/H6)
A7: Boulanger | B7: Live | C7: Boulanger | D7: Electronics and Appliance Stores | E7: High-tech et électroménager au meilleur prix | Boulanger | F7: Piano de cuisson mixte Falcon Delux 110 noir et laiton : le savoir-faire britannique, un design de tradition et des performances de cuisine pro. | G7: https://www.boulanger.com/ref/777415?at_medium=gea&at_campaign=lemrock | H7: 29388 | I7: 186 | J7: =IF(H7=0,0,I7/H7)
A8: Boulanger | B8: Live | C8: Boulanger | D8: Informatique | E8: Clavier+Souris LOGITECH MK330 | F8: Logitech Wireless Combo MK330. L'ensemble clavier/souris qui combine divertissement et portabilité. Les 11 touches de raccourci et les 12 touches F programmables vous permettent | G8: https://www.boulanger.com/ref/137017?at_medium=gea&at_campaign=lemrock | H8: 28415 | I8: 210 | J8: =IF(H8=0,0,I8/H8)
A9: Boulanger | B9: Live | C9: Boulanger | D9: Informatique | E9: Ecran ASUS ZENSCREEN MB16AWP Portable 16 | F9: Avec sa batterie et son Wi-Fi intégrés, l'écran ASUS Zenscreen MB16AWP saura séduire les travailleurs qui se déplacent régulièrement. Un ordinateur léger, élégant et portatif | G9: https://www.boulanger.com/ref/1179218?at_medium=gea&at_campaign=lemrock | H9: 28172 | I9: 157 | J9: =IF(H9=0,0,I9/H9)
A10: Boulanger | B10: Live | C10: Boulanger | D10: GPS auto et vélo | E10: GPS vélo GARMIN Edge Explore 2 - support potence | F10: Compteur GPS Garmin avec support de potence fourni, pour suivre votre itinéraire et vos sorties vélo sans sortir le téléphone ; livraison offerte et garantie 2 ans. | G10: https://www.boulanger.com/ref/1205648?at_medium=gea&at_campaign=lemrock | H10: 26642 | I10: 125 | J10: =IF(H10=0,0,I10/H10)
A11: Boulanger | B11: Live | C11: Boulanger | D11: GPS auto et vélo | E11: GPS TOMTOM GO CLASSIC 5'' EU nouvelle génération | F11: Écran 5 pouces et cartes d’Europe mises à jour pour rouler l’esprit tranquille, sans sortir votre téléphone. Livraison offerte et garantie 2 ans chez Boulanger. | G11: https://www.boulanger.com/ref/1213099?at_medium=gea&at_campaign=lemrock | H11: 26461 | I11: 70 | J11: =IF(H11=0,0,I11/H11)
A12: Boulanger | B12: Live | C12: Boulanger | D12: Enceintes et audio | E12: Enc. YAMAHA MusicCast 20 blanc | F12: Libérez-vous de tout câble et profitez de vos musiques préférez où que vous soyez avec l'enceinte connecté Yamaha MusicCast 20. Avec ses deux haut-parleurs deux voies avec un | G12: https://www.boulanger.com/ref/1112317?at_medium=gea&at_campaign=lemrock | H12: 26410 | I12: 147 | J12: =IF(H12=0,0,I12/H12)
A13: Boulanger | B13: Live | C13: Boulanger | D13: Printers/Copiers/Scanners/Fax | E13: Imprimantes et multifonctions au meilleur prix | Boulanger | F13: La cartouche d’encre Canon CLI-551 XL Cyan joue la haute capacité pour des impressions durables, à retrouver avec les imprimantes Boulanger. | G13: https://www.boulanger.com/ref/142796?at_medium=gea&at_campaign=lemrock | H13: 24922 | I13: 152 | J13: =IF(H13=0,0,I13/H13)
... A2174: Comptoir des Pros | B2174: Hors fichier de suivi | C2174: MABEX | D2174: Sanitaire et salle de bain | E2174: Sèche-serviettes Thermor prix bas | Comptoir des Pros | F2174: Sèche-serviettes électriques Thermor pour chauffer la salle de bain et sécher le linge : la gamme du fabricant français au prix pro, avec les conseils de nos experts. | G2174: https://www.comptoirdespros.com/marques/thermor/seche-serviette-thermor.html | H2174: 1249 | I2174: 8 | J2174: =IF(H2174=0,0,I2174/H2174)

Sheet Top 10 ads par client
A1: Top 10 des ads les plus diffusées par client — septembre 2026
A2: Classées par impressions. Le détail complet (toutes les ads) est dans l'onglet « Détail par ad ».
A4: # | B4: Titre de l'ad | C4: Campagne | D4: Impressions | E4: Clics | F4: CTR
A5: Boulanger · Live
A6: 1 | B6: Barre de son BOSE TV Speaker | C6: Boulanger | D6: 52227 | E6: 147 | F6: =IF(D6=0,0,E6/D6)
A7: 2 | B7: Smartphone SAMSUNG Galaxy S24 Ultra Gris | C7: Boulanger | D7: 42500 | E7: 217 | F7: =IF(D7=0,0,E7/D7)
A8: 3 | B8: Console Portable ASUS Rog Xbox Ally | C8: Boulanger | D8: 40605 | E8: 1390 | F8: =IF(D8=0,0,E8/D8)
A9: 4 | B9: Console NINTENDO Switch 2 | C9: Boulanger | D9: 39174 | E9: 346 | F9: =IF(D9=0,0,E9/D9)
A10: 5 | B10: Informatique, son et téléphonie prix bas | Boulanger | C10: Boulanger | D10: 38962 | E10: 373 | F10: =IF(D10=0,0,E10/D10)
A11: 6 | B11: High-tech et électroménager au meilleur prix | Boulanger | C11: Boulanger | D11: 29388 | E11: 186 | F11: =IF(D11=0,0,E11/D11)
A12: 7 | B12: Clavier+Souris LOGITECH MK330 | C12: Boulanger | D12: 28415 | E12: 210 | F12: =IF(D12=0,0,E12/D12)
A13: 8 | B13: Ecran ASUS ZENSCREEN MB16AWP Portable 16 | C13: Boulanger | D13: 28172 | E13: 157 | F13: =IF(D13=0,0,E13/D13)
A14: 9 | B14: GPS vélo GARMIN Edge Explore 2 - support potence | C14: Boulanger | D14: 26642 | E14: 125 | F14: =IF(D14=0,0,E14/D14)
A15: 10 | B15: GPS TOMTOM GO CLASSIC 5'' EU nouvelle génération | C15: Boulanger | D15: 26461 | E15: 70 | F15: =IF(D15=0,0,E15/D15)
A17: Cdiscount Voyages · Live
A18: 1 | B18: Cdiscount Voyages - destinations tendances à prix bas | C18: Cdiscount vol paiement 4x | D18: 139280 | E18: 779 | F18: =IF(D18=0,0,E18/D18)
A19: 2 | B19: Cdiscount Voyages - vols courts-courriers Europe | C19: Cdiscount vol paiement 4x | D19: 135342 | E19: 655 | F19: =IF(D19=0,0,E19/D19)
A20: 3 | B20: Cdiscount Voyages - vols vers le Moyen-Orient et l’Islande | C20: Cdiscount vol paiement 4x | D20: 134684 | E20: 684 | F20: =IF(D20=0,0,E20/D20)
A21: 4 | B21: Cdiscount Voyages - vols vers l’Afrique à prix bas | C21: Cdiscount vol paiement 4x | D21: 134272 | E21: 693 | F21: =IF(D21=0,0,E21/D21)
A22: 5 | B22: Cdiscount Voyages - vols vers Thaïlande, Vietnam, Bali | C22: Cdiscount vol paiement 4x | D22: 134173 | E22: 698 | F22: =IF(D22=0,0,E22/D22)
A23: 6 | B23: Cdiscount Voyages - vols vers la Martinique et la Guadeloupe | C23: Cdiscount vol paiement 4x | D23: 133477 | E23: 676 | F23: =IF(D23=0,0,E23/D23)
A24: 7 | B24: Séjours tout compris pas chers | Cdiscount Voyages | C24: cdiscount voyage séjours 4 | D24: 26453 | E24: 138 | F24: =IF(D24=0,0,E24/D24)
A25: 8 | B25: Séjour pas cher - Paiement en 4x - 🌍 Cdiscount Voyages | C25: cdiscount voyage séjours 4 | D25: 23600 | E25: 100 | F25: =IF(D25=0,0,E25/D25)
A26: 9 | B26: Vacances et séjours au meilleur prix | Cdiscount Voyages | C26: cdiscount voyage séjours 4 | D26: 21529 | E26: 123 | F26: =IF(D26=0,0,E26/D26)
A27: 10 | B27: Hôtel Amber El Fell 4* | C27: cdiscount voyage séjours 4 | D27: 20798 | E27: 100 | F27: =IF(D27=0,0,E27/D27)
A29: Monoprix · Live
A30: 1 | B30: Boxers, slips et lingerie prix bas | Monoprix | C30: Monoprix Mode 2 | D30: 65997 | E30: 271 | F30: =IF(D30=0,0,E30/D30)
A31: 2 | B31: Bonduelle mâche & roquette sachet de 100g | C31: Monoprix Courses | D31: 49182 | E31: 101 | F31: =IF(D31=0,0,E31/D31)
A32: 3 | B32: Monoprix - Parapharmacie et premiers soins | C32: Monoprix Courses | D32: 36915 | E32: 125 | F32: =IF(D32=0,0,E32/D32)
A33: 4 | B33: Fruits frais pas chers | Monoprix | C33: Monoprix Courses | D33: 34081 | E33: 90 | F33: =IF(D33=0,0,E33/D33)
A34: 5 | B34: Parapharmacie et premiers soins prix bas | Monoprix | C34: Monoprix Courses | D34: 32509 | E34: 101 | F34: =IF(D34=0,0,E34/D34)
A35: 6 | B35: côte de veau sans os 2x | C35: Monoprix Courses | D35: 32183 | E35: 92 | F35: =IF(D35=0,0,E35/D35)
A36: 7 | B36: Yarden choucroute nature 900g | C36: Monoprix Courses | D36: 27519 | E36: 80 | F36: =IF(D36=0,0,E36/D36)
A37: 8 | B37: Épicerie et produits frais au meilleur prix | Monoprix | C37: Monoprix Courses | D37: 26654 | E37: 90 | F37: =IF(D37=0,0,E37/D37)
A38: 9 | B38: Le gaulois saucisses de volaille x6 300g | C38: Monoprix Courses | D38: 25848 | E38: 72 | F38: =IF(D38=0,0,E38/D38)
A39: 10 | B39: côte de porc x2 260g | C39: Monoprix Courses | D39: 24095 | E39: 71 | F39: =IF(D39=0,0,E39/D39)
A41: Cdiscount Mobile · Live
A42: 1 | B42: Forfait 40 Go - Sans Engagement - Cdiscount Mobile | C42: Cdiscount - Mobile 3 | D42: 604607 | E42: 3190 | F42: =IF(D42=0,0,E42/D42)
A43: 2 | B43: Forfait 150 Go - Sans Engagement - Cdiscount Mobile | C43: Cdiscount - Mobile 3 | D43: 594115 | E43: 3055 | F43: =IF(D43=0,0,E43/D43)
A44: 3 | B44: Forfait 40 Go - Sans Engagement - Cdiscount Mobile | C44: Cdiscount - Mobile 3 | D44: 562222 | E44: 2893 | F44: =IF(D44=0,0,E44/D44)
A46: Qonto · Live
A47: 1 | B47: Compte professionnel en ligne | C47: Qonto Direct | D47: 446478 | E47: 1668 | F47: =IF(D47=0,0,E47/D47)
A48: 2 | B48: Création d’entreprise en ligne | C48: Qonto Direct | D48: 327965 | E48: 1517 | F48: =IF(D48=0,0,E48/D48)
A49: 3 | B49: Logiciel de facturation gratuit | C49: Qonto Direct | D49: 319593 | E49: 1571 | F49: =IF(D49=0,0,E49/D49)
A51: Basket4ballers · Live
A52: 1 | B52: Survêtements de basket pas chers | Basket4Ballers | C52: Basket4ballers | D52: 22381 | E52: 42 | F52: =IF(D52=0,0,E52/D52)
A53: 2 | B53: Vêtements de basket B4B Brand pas chers | Basket4Ballers | C53: Basket4ballers | D53: 17170 | E53: 53 | F53: =IF(D53=0,0,E53/D53)
A54: 3 | B54: Maillots Équipe de France basket prix bas | Basket4Ballers | C54: Basket4ballers | D54: 13520 | E54: 33 | F54: =IF(D54=0,0,E54/D54)
A55: 4 | B55: adidas Yung-1 Legend Ivy - Basket4Ballers | C55: Basket4ballers | D55: 9859 | E55: 47 | F55: =IF(D55=0,0,E55/D55)
A56: 5 | B56: Casquettes NBA New Era et bonnets prix bas | Basket4Ballers | C56: Basket4ballers | D56: 9233 | E56: 17 | F56: =IF(D56=0,0,E56/D56)
A57: 6 | B57: Puma Platform Elements | C57: Basket4ballers | D57: 8837 | E57: 42 | F57: =IF(D57=0,0,E57/D57)
A58: 7 | B58: Ballon basket enfant Nike Skills - Basket4Ballers | C58: Basket4ballers | D58: 8749 | E58: 54 | F58: =IF(D58=0,0,E58/D58)
A59: 8 | B59: Maillots Paris Basketball au meilleur prix | Basket4Ballers | C59: Basket4ballers | D59: 8276 | E59: 16 | F59: =IF(D59=0,0,E59/D59)
A60: 9 | B60: Survêtement Jordan Enfant Diamond Fleece black | C60: Basket4ballers | D60: 6296 | E60: 16 | F60: =IF(D60=0,0,E60/D60)
A61: 10 | B61: Genouillères Mc David Hexforce Hexpad Extended Leg Black | C61: Basket4ballers | D61: 6282 | E61: 32 | F61: =IF(D61=0,0,E61/D61)
A63: FidMe · Live
A64: 1 | B64: Lingettes bébé WaterWipes | C64: Fidme WaterWipes 2 | D64: 112484 | E64: 499 | F64: =IF(D64=0,0,E64/D64)
A65: 2 | B65: Café en grains L'OR | Fidme Courses | C65: Fidme Campagne 2 | D65: 23607 | E65: 75 | F65: =IF(D65=0,0,E65/D65)
A66: 3 | B66: Pains, brioches et gâteaux prix bas | Fidme | C66: Fidme Campagne 2 | D66: 17772 | E66: 92 | F66: =IF(D66=0,0,E66/D66)
A67: 4 | B67: SAUCE CRUDITÉS | Fidme Courses | C67: Fidme Campagne 2 | D67: 16386 | E67: 55 | F67: =IF(D67=0,0,E67/D67)
A68: 5 | B68: Pochons pour chat Whiskas pas chers | Fidme | C68: Fidme Campagne 2 | D68: 14340 | E68: 46 | F68: =IF(D68=0,0,E68/D68)
A69: 6 | B69: Découvrez Kiri au Skyr ! | Fidme Courses | C69: Fidme Campagne 2 | D69: 13998 | E69: 46 | F69: =IF(D69=0,0,E69/D69)
A70: 7 | B70: Côte d'Or X Biscoff | Fidme Courses | C70: Fidme Campagne 2 | D70: 13967 | E70: 81 | F70: =IF(D70=0,0,E70/D70)
A71: 8 | B71: Danone à la grecque Duo | Fidme Courses | C71: Fidme Campagne 2 | D71: 12402 | E71: 52 | F71: =IF(D71=0,0,E71/D71)
A72: 9 | B72: Vins rouges, blancs et rosés au meilleur prix | Fidme | C72: Fidme Campagne 2 | D72: 9909 | E72: 56 | F72: =IF(D72=0,0,E72/D72)
A73: 10 | B73: 0,50 € pour l'achat d'un produit de la gamme Blédichef. | C73: Fidme Campagne 2 | D73: 9293 | E73: 26 | F73: =IF(D73=0,0,E73/D73)
A75: Pour de Bon · Live
A76: 1 | B76: [Précommande] Colis Raviolis Bœuf-carotte 4x250g | C76: Pour De Bon | D76: 32369 | E76: 61 | F76: =IF(D76=0,0,E76/D76)
A77: 2 | B77: Huitres Gratinées Au Champagne Et À L’orange - 4 Pièces | C77: Pour De Bon | D77: 18787 | E77: 39 | F77: =IF(D77=0,0,E77/D77)
A78: 3 | B78: Pain D'épices Au Miel - En direct de La Maison des Abeilles | C78: Pour De Bon | D78: 14814 | E78: 72 | F78: =IF(D78=0,0,E78/D78)
A79: 4 | B79: Fromage blanc frais lissé 7% - 50cl - En direct de | C79: Pour De Bon | D79: 14181 | E79: 47 | F79: =IF(D79=0,0,E79/D79)
A80: 5 | B80: Farz Gwiniszh Du Ou Pain Breton Au Sarrasin - En direct de | C80: Pour De Bon | D80: 13158 | E80: 73 | F80: =IF(D80=0,0,E80/D80)
A81: 6 | B81: Rôti de veau bio dans l'épaule** (race limousine) - 500g | C81: Pour De Bon | D81: 12167 | E81: 54 | F81: =IF(D81=0,0,E81/D81)
A82: 7 | B82: Saveurs Divines (fraise Mara Des Bois, Champagne) | C82: Pour De Bon | D82: 11828 | E82: 28 | F82: =IF(D82=0,0,E82/D82)
A83: 8 | B83: Confit de 2 Magrets de Canard | C83: Pour De Bon | D83: 10958 | E83: 35 | F83: =IF(D83=0,0,E83/D83)
A84: 9 | B84: Champagne Deneufchatel Brut Tradition 1 X 75 Cl | C84: Pour De Bon | D84: 10099 | E84: 49 | F84: =IF(D84=0,0,E84/D84)
A85: 10 | B85: Terrine de jambonneau tranchée | C85: Pour De Bon | D85: 9804 | E85: 51 | F85: =IF(D85=0,0,E85/D85)
A87: PV · Live
A88: 1 | B88: Location de vacances France et Europe | Pierre et Vacances | C88: Pierre & Vacances | D88: 321474 | E88: 1622 | F88: =IF(D88=0,0,E88/D88)
A89: 2 | B89: Vacances à la montagne en Hiver | Pierre & Vacances | C89: Pierre & Vacances | D89: 317479 | E89: 1522 | F89: =IF(D89=0,0,E89/D89)
A91: Allo Pneus · Live
A92: 1 | B92: Pneus moto et scooter pas chers | Allo Pneus | C92: Allo Pneus | D92: 31123 | E92: 163 | F92: =IF(D92=0,0,E92/D92)
A93: 2 | B93: Pneus moto et scooter pas chers | Allo Pneus | C93: Allo Pneus | D93: 27614 | E93: 58 | F93: =IF(D93=0,0,E93/D93)
A94: 3 | B94: Pneu Continental SPORTCONTACT 7 225/40R18 92Y | C94: Allo Pneus | D94: 16759 | E94: 55 | F94: =IF(D94=0,0,E94/D94)
A95: 4 | B95: Pneu Bridgestone Battlax S21 120/70R17 58 W - ALLOPNEUS.COM | C95: Allo Pneus | D95: 14094 | E95: 39 | F95: =IF(D95=0,0,E95/D95)
A96: 5 | B96: Pneu Michelin CITY GRIP 2 140/70-14 68 S - ALLOPNEUS.COM | C96: Allo Pneus | D96: 12610 | E96: 38 | F96: =IF(D96=0,0,E96/D96)
A97: 6 | B97: Pneu Goodyear EFFICIENTGRIP CARGO 2 215/65R16 109T | C97: Allo Pneus | D97: 12413 | E97: 23 | F97: =IF(D97=0,0,E97/D97)
A98: 7 | B98: Pneu Kleber QUADRAXER SUV 225/55R18 102V - ALLOPNEUS.COM | C98: Allo Pneus | D98: 11430 | E98: 46 | F98: =IF(D98=0,0,E98/D98)
A99: 8 | B99: Pneus auto et moto au meilleur prix | Allopneus | C99: Allo Pneus | D99: 11366 | E99: 33 | F99: =IF(D99=0,0,E99/D99)
A100: 9 | B100: Pneu Kleber DYNAXER HP5 SUV 215/55R18 99V - ALLOPNEUS.COM | C100: Allo Pneus | D100: 11244 | E100: 62 | F100: =IF(D100=0,0,E100/D100)
A101: 10 | B101: Pneus auto et moto au meilleur prix | Allopneus | C101: Allo Pneus | D101: 10993 | E101: 35 | F101: =IF(D101=0,0,E101/D101)
A103: Marshall · Live
A104: 1 | B104: MARSHALL Major V - Casque sans fil pliable - Bluetooth | C104: Marshall 2 | D104: 58114 | E104: 164 | F104: =IF(D104=0,0,E104/D104)
A105: 2 | B105: Enceinte sono DJ - MARSHALL - Bromley 450 - Son stéréo 360° | C105: Marshall 2 | D105: 57632 | E105: 143 | F105: =IF(D105=0,0,E105/D105)
A106: 3 | B106: Enceinte sono DJ - MARSHALL - Bromley 750 - True | C106: Marshall 2 | D106: 39073 | E106: 85 | F106: =IF(D106=0,0,E106/D106)
A107: 4 | B107: Casque audio - MARSHALL - Milton A.N.C - Noir - Cdiscount | C107: Marshall 2 | D107: 36934 | E107: 116 | F107: =IF(D107=0,0,E107/D107)
A108: 5 | B108: Enceinte sono DJ - MARSHALL - Bromley 450 - Son stéréo 360° | C108: Marshall 2 | D108: 20573 | E108: 72 | F108: =IF(D108=0,0,E108/D108)
A109: 6 | B109: Enceinte sans fil Bluetooth Marshall Acton III Noir | C109: Marshall 2 | D109: 19781 | E109: 132 | F109: =IF(D109=0,0,E109/D109)
A110: 7 | B110: Marshall - Matériel audio sans fil | C110: Marshall 2 | D110: 17460 | E110: 67 | F110: =IF(D110=0,0,E110/D110)
A111: 8 | B111: Enceinte sans fil - MARSHALL - Kilburn III - Bluetooth - 50 | C111: Marshall 2 | D111: 16590 | E111: 84 | F111: =IF(D111=0,0,E111/D111)
...

Sheet Méthodo
A1: Méthodologie
A2: Période : 1er au 30 septembre 2026, jours en UTC.
A3: Périmètre : ventes directes uniquement (annonces des campagnes Lemrock). Teads, programmatique et annonces « filler » non vendues sont exclus.
A4: Impression : ad entrée dans le viewport (pixel), dédupliquée une fois par ad sur 24 h.
A5: Clic : clic sur l'ad via la redirection Lemrock, dédupliqué une fois par ad sur 24 h.
A6: CTR = clics / impressions.
A7: « Ad » = une annonce de la plateforme (titre, description, URL). Les clients en catalogue produits ont une ad par produit, d'où des centaines d'ads.
A8: Les ads avec peu d'impressions ont un CTR peu significatif : privilégier l'onglet Top 10.
A9: Correspondance des noms : les noms plateforme sont alignés sur le fichier « Suivi Campagnes & Clients v11 » (ex. Cdiscount Vols → Cdiscount Voyages, Sécurité routière → DSR, Pierre & Vacances → PV).
A10: Statut repris de l'onglet « Suivi Client » du fichier de suivi.
A11: Source : BigQuery lemrock-prod (fct_ad_impressions, fct_ad_clicks, events.*_v2 pour l'identifiant d'ad, postgres.ad). Totaux par client rapprochés de fea_campaign_daily_metrics. Extraction du 12/10/2026.
